LLM_demo_2_production/__init__.py
LLM_demo_2_production/_modidx.py
LLM_demo_2_production/social_media_automator/__init__.py
LLM_demo_2_production/social_media_automator/autogpt.py
LLM_demo_2_production/social_media_automator/generate_sm_content.py
LLM_demo_2_production/social_media_automator/mrkl.py
LLM_demo_2_production/social_media_automator/qa.py
LLM_demo_2_production-0.0.1.dist-info/LICENSE
LLM_demo_2_production-0.0.1.dist-info/METADATA
LLM_demo_2_production-0.0.1.dist-info/WHEEL
LLM_demo_2_production-0.0.1.dist-info/entry_points.txt
LLM_demo_2_production-0.0.1.dist-info/top_level.txt
LLM_demo_2_production-0.0.1.dist-info/RECORD
