Metadata-Version: 2.1
Name: LLM-demo-2-production
Version: 0.0.1
Home-page: https://github.com/laugustyniak/LLM-demo-2-production
Author: Łukasz Augustyniak
Author-email: aisolutions@lukaszaugustyniak.com
License: apache2
Keywords: LLM production demo
Classifier: Development Status :: 4 - Beta
Classifier: Intended Audience :: Developers
Classifier: Natural Language :: English
Classifier: Programming Language :: Python :: 3.8
Classifier: Programming Language :: Python :: 3.9
Classifier: Programming Language :: Python :: 3.10
Requires-Python: >=3.8
License-File: LICENSE
Provides-Extra: dev
